setup.py
funfunfun/__init__.py
funfunfun.egg-info/PKG-INFO
funfunfun.egg-info/SOURCES.txt
funfunfun.egg-info/dependency_links.txt
funfunfun.egg-info/not-zip-safe
funfunfun.egg-info/top_level.txt