Metadata-Version: 1.0
Name: funfunfun
Version: 0.1
Summary: it's lots of fun
Home-page: example.com
Author: luo
Author-email: luo.sh@foxmail.com
License: MIT
Platform: UNKNOWN
